cubicweb_api/__init__.py
cubicweb_api/__pkginfo__.py
cubicweb_api/constants.py
cubicweb_api/exceptions.py
cubicweb_api/httperrors.py
cubicweb_api/predicates.py
cubicweb_api/routes.py
cubicweb_api/transaction.py
cubicweb_api/util.py
cubicweb_api/auth/__init__.py
cubicweb_api/auth/jwt.py
cubicweb_api/auth/jwt_policy.py
cubicweb_api/auth/routes.py
cubicweb_api/i18n/en.po
cubicweb_api/i18n/es.po
cubicweb_api/i18n/fr.po
cubicweb_api/migration/postcreate.py
cubicweb_api/openapi/__init__.py
cubicweb_api/openapi/openapi.py
cubicweb_api/openapi/openapi_template.yaml
cubicweb_api-0.17.1.dist-info/METADATA
cubicweb_api-0.17.1.dist-info/WHEEL
cubicweb_api-0.17.1.dist-info/entry_points.txt
cubicweb_api-0.17.1.dist-info/top_level.txt
cubicweb_api-0.17.1.dist-info/RECORD
