Metadata-Version: 2.4
Name: cubicweb-api
Version: 0.17.1
Summary: This cube is the new api.
Author-email: Logilab <contact@logilab.fr>
License: GNU Lesser General Public License v2 or later (LGPLv2+)
Project-URL: Issues, https://forge.extranet.logilab.fr/cubicweb/cubes/api/-/issues
Project-URL: Repository, https://forge.extranet.logilab.fr/cubicweb/cubes/api
Classifier: Environment :: Web Environment
Classifier: Framework :: CubicWeb
Classifier: Programming Language :: Python
Classifier: Programming Language :: Python :: 3
Classifier: Programming Language :: Python :: 3 :: Only
Classifier: Programming Language :: JavaScript
Requires-Python: >=3.11
Requires-Dist: cubicweb<6.0.0,>=4.1.0
Requires-Dist: yams>=0.49.3
Requires-Dist: PyJWT>=2.4.0
Requires-Dist: pyramid-openapi3>=0.19.1
Requires-Dist: openapi-core>=0.17.0
